genskew/__init__.py
genskew/__main__.py
Genskew_cc-0.1.2.dist-info/LICENSE
Genskew_cc-0.1.2.dist-info/METADATA
Genskew_cc-0.1.2.dist-info/WHEEL
Genskew_cc-0.1.2.dist-info/top_level.txt
Genskew_cc-0.1.2.dist-info/RECORD
