Metadata-Version: 2.1
Name: Genskew-cc
Version: 0.1.2
Summary: A program that calculates genskew.
Home-page: https://genskew.csb.univie.ac.at/genskew_cc
Author: Thomas Rattei, Julius Krämer
License: Creative Commons
Platform: UNKNOWN
Classifier: Programming Language :: Python :: 3
Classifier: Operating System :: OS Independent
Requires-Python: >=3.6
License-File: LICENSE
Requires-Dist: matplotlib
Requires-Dist: Biopython
Requires-Dist: argparse
Requires-Dist: Genskew-univiecube
Requires-Dist: GUIskew
